{
  "Angels": 6.6,
  "Astros": 100.0,
  "Athletics": 0.0,
  "Blue Jays": 83.4,
  "Braves": 97.7,
  "Brewers": 87.4,
  "Cardinals": 35.3,
  "Cubs": 0.1,
  "Diamondbacks": 0.1,
  "Dodgers": 99.7,
  "Giants": 33.3,
  "Guardians": 25.1,
  "Mariners": 39.5,
  "Marlins": 6.6,
  "Mets": 98.9,
  "Nationals": 0.0,
  "Orioles": 1.1,
  "Padres": 88.3,
  "Phillies": 52.5,
  "Pirates": 0.0,
  "Rangers": 4.3,
  "Rays": 60.5,
  "Red Sox": 71.9,
  "Reds": 0.0,
  "Rockies": 0.0,
  "Royals": 0.1,
  "Tigers": 0.6,
  "Twins": 59.1,
  "White Sox": 47.9,
  "Yankees": 100.0
}