{
  "Angels": 63.2,
  "Astros": 80.9,
  "Athletics": 1.7,
  "Blue Jays": 93.8,
  "Braves": 72.0,
  "Brewers": 82.2,
  "Cardinals": 41.2,
  "Cubs": 5.6,
  "Diamondbacks": 0.3,
  "Dodgers": 94.0,
  "Giants": 68.0,
  "Guardians": 13.1,
  "Mariners": 40.5,
  "Marlins": 26.7,
  "Mets": 84.9,
  "Nationals": 0.0,
  "Orioles": 0.0,
  "Padres": 80.4,
  "Phillies": 42.7,
  "Pirates": 0.3,
  "Rangers": 1.8,
  "Rays": 47.9,
  "Red Sox": 46.2,
  "Reds": 0.6,
  "Rockies": 0.9,
  "Royals": 5.4,
  "Tigers": 5.0,
  "Twins": 54.3,
  "White Sox": 55.7,
  "Yankees": 90.5
}