{
  "Angels": 57.7,
  "Astros": 97.2,
  "Athletics": 0.1,
  "Blue Jays": 92.7,
  "Braves": 68.6,
  "Brewers": 93.2,
  "Cardinals": 47.5,
  "Cubs": 1.7,
  "Diamondbacks": 1.1,
  "Dodgers": 99.0,
  "Giants": 63.1,
  "Guardians": 9.5,
  "Mariners": 8.9,
  "Marlins": 10.5,
  "Mets": 93.4,
  "Nationals": 0.1,
  "Orioles": 0.0,
  "Padres": 92.9,
  "Phillies": 28.2,
  "Pirates": 0.2,
  "Rangers": 3.7,
  "Rays": 69.2,
  "Red Sox": 36.3,
  "Reds": 0.3,
  "Rockies": 0.2,
  "Royals": 0.4,
  "Tigers": 0.6,
  "Twins": 62.5,
  "White Sox": 63.7,
  "Yankees": 97.5
}