{
  "Angels": 65.0,
  "Astros": 82.2,
  "Athletics": 1.4,
  "Blue Jays": 94.8,
  "Braves": 75.3,
  "Brewers": 81.3,
  "Cardinals": 44.5,
  "Cubs": 4.2,
  "Diamondbacks": 0.3,
  "Dodgers": 93.3,
  "Giants": 68.1,
  "Guardians": 11.7,
  "Mariners": 37.7,
  "Marlins": 25.7,
  "Mets": 84.1,
  "Nationals": 0.1,
  "Orioles": 0.0,
  "Padres": 79.8,
  "Phillies": 41.9,
  "Pirates": 0.3,
  "Rangers": 1.4,
  "Rays": 52.5,
  "Red Sox": 42.4,
  "Reds": 0.5,
  "Rockies": 0.8,
  "Royals": 6.2,
  "Tigers": 5.4,
  "Twins": 56.3,
  "White Sox": 50.7,
  "Yankees": 92.3
}