{
  "Angels": 11.1,
  "Astros": 100.0,
  "Athletics": 0.0,
  "Blue Jays": 91.8,
  "Braves": 95.0,
  "Brewers": 88.7,
  "Cardinals": 47.0,
  "Cubs": 0.1,
  "Diamondbacks": 0.1,
  "Dodgers": 98.7,
  "Giants": 40.8,
  "Guardians": 29.0,
  "Mariners": 15.7,
  "Marlins": 8.5,
  "Mets": 97.6,
  "Nationals": 0.0,
  "Orioles": 0.2,
  "Padres": 86.2,
  "Phillies": 37.3,
  "Pirates": 0.0,
  "Rangers": 4.4,
  "Rays": 57.7,
  "Red Sox": 79.1,
  "Reds": 0.0,
  "Rockies": 0.0,
  "Royals": 0.0,
  "Tigers": 0.3,
  "Twins": 60.3,
  "White Sox": 50.4,
  "Yankees": 100.0
}