{
  "Angels": 39.7,
  "Astros": 91.6,
  "Athletics": 1.2,
  "Blue Jays": 89.4,
  "Braves": 88.6,
  "Brewers": 74.6,
  "Cardinals": 42.3,
  "Cubs": 8.1,
  "Diamondbacks": 0.2,
  "Dodgers": 88.6,
  "Giants": 56.5,
  "Guardians": 19.8,
  "Mariners": 22.5,
  "Marlins": 16.8,
  "Mets": 77.4,
  "Nationals": 0.6,
  "Orioles": 0.1,
  "Padres": 80.1,
  "Phillies": 58.4,
  "Pirates": 0.6,
  "Rangers": 5.1,
  "Rays": 53.8,
  "Red Sox": 56.6,
  "Reds": 6.3,
  "Rockies": 1.0,
  "Royals": 9.1,
  "Tigers": 8.6,
  "Twins": 34.7,
  "White Sox": 77.0,
  "Yankees": 90.9
}