{
  "Angels": 71.8,
  "Astros": 91.3,
  "Athletics": 0.2,
  "Blue Jays": 94.9,
  "Braves": 68.1,
  "Brewers": 95.2,
  "Cardinals": 51.4,
  "Cubs": 1.6,
  "Diamondbacks": 1.8,
  "Dodgers": 97.0,
  "Giants": 57.2,
  "Guardians": 15.6,
  "Mariners": 18.3,
  "Marlins": 16.8,
  "Mets": 89.9,
  "Nationals": 0.2,
  "Orioles": 0.0,
  "Padres": 85.3,
  "Phillies": 33.6,
  "Pirates": 0.2,
  "Rangers": 2.2,
  "Rays": 62.1,
  "Red Sox": 25.7,
  "Reds": 0.1,
  "Rockies": 1.6,
  "Royals": 2.2,
  "Tigers": 2.7,
  "Twins": 57.0,
  "White Sox": 60.3,
  "Yankees": 95.7
}