{
  "Angels": 59.9,
  "Astros": 79.1,
  "Athletics": 1.4,
  "Blue Jays": 95.4,
  "Braves": 77.6,
  "Brewers": 80.9,
  "Cardinals": 38.1,
  "Cubs": 5.2,
  "Diamondbacks": 0.2,
  "Dodgers": 95.3,
  "Giants": 73.0,
  "Guardians": 16.8,
  "Mariners": 46.3,
  "Marlins": 23.5,
  "Mets": 87.0,
  "Nationals": 0.1,
  "Orioles": 0.0,
  "Padres": 77.2,
  "Phillies": 39.0,
  "Pirates": 0.6,
  "Rangers": 2.5,
  "Rays": 45.7,
  "Red Sox": 45.2,
  "Reds": 1.0,
  "Rockies": 1.1,
  "Royals": 7.8,
  "Tigers": 7.9,
  "Twins": 47.3,
  "White Sox": 54.0,
  "Yankees": 90.7
}