{
  "Angels": 56.6,
  "Astros": 85.2,
  "Athletics": 2.1,
  "Blue Jays": 91.7,
  "Braves": 80.8,
  "Brewers": 78.5,
  "Cardinals": 46.8,
  "Cubs": 6.7,
  "Diamondbacks": 0.3,
  "Dodgers": 95.8,
  "Giants": 61.0,
  "Guardians": 27.9,
  "Mariners": 29.7,
  "Marlins": 18.5,
  "Mets": 85.5,
  "Nationals": 0.5,
  "Orioles": 0.0,
  "Padres": 82.1,
  "Phillies": 39.9,
  "Pirates": 0.7,
  "Rangers": 2.5,
  "Rays": 42.8,
  "Red Sox": 57.3,
  "Reds": 1.4,
  "Rockies": 1.4,
  "Royals": 9.0,
  "Tigers": 7.6,
  "Twins": 28.4,
  "White Sox": 73.9,
  "Yankees": 85.2
}