{
  "Angels": 66.1,
  "Astros": 82.2,
  "Athletics": 1.5,
  "Blue Jays": 94.3,
  "Braves": 75.6,
  "Brewers": 82.2,
  "Cardinals": 43.6,
  "Cubs": 4.4,
  "Diamondbacks": 0.3,
  "Dodgers": 93.5,
  "Giants": 67.8,
  "Guardians": 12.0,
  "Mariners": 37.4,
  "Marlins": 25.9,
  "Mets": 83.8,
  "Nationals": 0.0,
  "Orioles": 0.0,
  "Padres": 79.7,
  "Phillies": 41.5,
  "Pirates": 0.3,
  "Rangers": 1.5,
  "Rays": 53.4,
  "Red Sox": 41.9,
  "Reds": 0.6,
  "Rockies": 0.8,
  "Royals": 6.1,
  "Tigers": 5.3,
  "Twins": 56.3,
  "White Sox": 50.5,
  "Yankees": 91.6
}