{
  "Angels": 72.3,
  "Astros": 96.9,
  "Athletics": 0.2,
  "Blue Jays": 87.7,
  "Braves": 66.5,
  "Brewers": 95.6,
  "Cardinals": 37.6,
  "Cubs": 1.4,
  "Diamondbacks": 1.8,
  "Dodgers": 97.1,
  "Giants": 70.2,
  "Guardians": 15.3,
  "Mariners": 11.4,
  "Marlins": 12.9,
  "Mets": 87.8,
  "Nationals": 0.1,
  "Orioles": 0.1,
  "Padres": 89.6,
  "Phillies": 38.3,
  "Pirates": 0.2,
  "Rangers": 3.8,
  "Rays": 60.8,
  "Red Sox": 30.0,
  "Reds": 0.3,
  "Rockies": 0.6,
  "Royals": 1.2,
  "Tigers": 0.7,
  "Twins": 56.0,
  "White Sox": 64.7,
  "Yankees": 99.0
}