{
  "Angels": 23.0,
  "Astros": 99.0,
  "Athletics": 0.0,
  "Blue Jays": 96.9,
  "Braves": 79.1,
  "Brewers": 82.6,
  "Cardinals": 49.3,
  "Cubs": 0.9,
  "Diamondbacks": 0.9,
  "Dodgers": 98.2,
  "Giants": 55.8,
  "Guardians": 23.7,
  "Mariners": 12.3,
  "Marlins": 8.8,
  "Mets": 94.5,
  "Nationals": 0.0,
  "Orioles": 0.0,
  "Padres": 93.4,
  "Phillies": 36.1,
  "Pirates": 0.2,
  "Rangers": 3.2,
  "Rays": 75.5,
  "Red Sox": 54.9,
  "Reds": 0.2,
  "Rockies": 0.1,
  "Royals": 0.2,
  "Tigers": 1.1,
  "Twins": 54.6,
  "White Sox": 55.9,
  "Yankees": 99.8
}