{
  "Angels": 57.2,
  "Astros": 98.3,
  "Athletics": 0.0,
  "Blue Jays": 94.7,
  "Braves": 61.1,
  "Brewers": 94.6,
  "Cardinals": 56.1,
  "Cubs": 1.2,
  "Diamondbacks": 2.1,
  "Dodgers": 98.4,
  "Giants": 71.7,
  "Guardians": 13.7,
  "Mariners": 10.1,
  "Marlins": 8.7,
  "Mets": 95.3,
  "Nationals": 0.1,
  "Orioles": 0.1,
  "Padres": 90.5,
  "Phillies": 19.3,
  "Pirates": 0.3,
  "Rangers": 7.5,
  "Rays": 64.0,
  "Red Sox": 31.3,
  "Reds": 0.4,
  "Rockies": 0.3,
  "Royals": 0.3,
  "Tigers": 0.7,
  "Twins": 61.5,
  "White Sox": 62.6,
  "Yankees": 98.0
}